{
  "keyword": "SVG秒转高清PNG神器",
  "competitors": [
    {
      "name": "SVG to PNG Converter by Convertio",
      "url": "https://convertio.co/svg-png/",
      "features": [
        "批量转换",
        "支持云存储（Google Drive, Dropbox）",
        "界面简洁直观",
        "支持多种输出格式"
      ],
      "weaknesses": [
        "免费版有文件大小和数量限制",
        "转换速度依赖网络",
        "高级功能需付费",
        "无中文界面"
      ],
      "pricing": "freemium",
      "monthly_traffic": 1200000
    },
    {
      "name": "OnlineConvertFree",
      "url": "https://onlineconvertfree.com/zh/convert/svg-to-png/",
      "features": [
        "完全免费，无限制",
        "界面全中文",
        "转换速度快",
        "无需注册"
      ],
      "weaknesses": [
        "广告较多，体验差",
        "输出分辨率选项有限",
        "无批量处理高级功能",
        "品牌感较弱"
      ],
      "pricing": "free",
      "monthly_traffic": 800000
    },
    {
      "name": "iLoveIMG - SVG转PNG",
      "url": "https://www.iloveimg.com/zh-cn/convert-to-png/svg-to-png",
      "features": [
        "集成在强大的图片处理工具集内",
        "可调整输出尺寸和DPI",
        "批量处理",
        "中文界面友好"
      ],
      "weaknesses": [
        "免费版有每小时处理次数限制",
        "核心功能需订阅",
        "转换流程步骤稍多"
      ],
      "pricing": "freemium",
      "monthly_traffic": 15000000
    },
    {
      "name": "AConvert SVG to PNG",
      "url": "https://www.aconvert.com/cn/image/svg-to-png/",
      "features": [
        "可自定义分辨率、背景色、质量",
        "技术参数选项非常详细",
        "支持URL直接转换",
        "隐私声明明确"
      ],
      "weaknesses": [
        "界面老旧，不美观",
        "操作对新手不友好",
        "无实时预览",
        "高级选项容易让用户困惑"
      ],
      "pricing": "free",
      "monthly_traffic": 500000
    },
    {
      "name": "SVG转PNG - 迅捷PDF转换器在线工具",
      "url": "https://app.xunjiepdf.com/svg2png/",
      "features": [
        "本土化好，完全针对中文用户",
        "宣传“高清”转换",
        "操作流程极简",
        "与其它格式转换工具联动"
      ],
      "weaknesses": [
        "免费版有水印",
        "强制关注公众号获取结果（部分情况）",
        "有文件数量限制",
        "工具集合站，专业性感觉不足"
      ],
      "pricing": "freemium",
      "monthly_traffic": 300000
    }
  ],
  "gaps": [
    {
      "gap": "缺乏针对设计工作流的智能预设与批量模板",
      "implementation": "开发“场景模式”，如“iOS应用图标包”（自动输出多种尺寸）、“社交媒体套图”（预设各平台最佳尺寸和格式）。允许用户创建和保存自定义转换模板，一键应用于批量文件。",
      "impact": "HIGH",
      "effort": "MEDIUM"
    },
    {
      "gap": "转换前后缺乏专业的视觉对比与质量检查工具",
      "implementation": "在转换界面提供并排的SVG原图与PNG输出结果的实时对比滑块（Before/After Slider），并加入放大镜细节对比功能。同时，集成一个简单的像素检查工具，提示是否有模糊、锯齿或颜色失真。",
      "impact": "MEDIUM",
      "effort": "SIMPLE"
    },
    {
      "gap": "没有专注于“极致高清”和“无损”转换的垂直化高端选项",
      "implementation": "提供一个“专业模式”，专注于超参数控制：如选择抗锯齿算法（Lanczos, Bicubic）、色彩空间配置（sRGB, Adobe RGB）、透明度处理优化、边缘锐化微调。明确宣传“无损矢量栅格化引擎”。",
      "impact": "MEDIUM",
      "effort": "COMPLEX"
    },
    {
      "gap": "免费模式体验割裂，存在强制行为或干扰性广告",
      "implementation": "采用更优雅的免费模式：免费用户享受无广告、无水印、无强制关注的基础高速转换，但单次处理有文件数量（如5个）和分辨率（如4K）上限。通过清晰的功能对比，引导用户为“无限批量”和“8K+专业参数”付费。",
      "impact": "HIGH",
      "effort": "SIMPLE"
    }
  ],
  "recommended_positioning": "专为设计师和开发者打造的智能SVG转高清PNG工具，提供场景化批量模板与无损画质对比，让转换既高效又专业。",
  "analyzed_at": "2026-03-09T18:13:23.592854"
}